{
  "project_info": {
    "project_number": "8400768666",
    "firebase_url": "https://pushproject-ea291.firebaseio.com",
    "project_id": "pushproject-ea291",
    "storage_bucket": "pushproject-ea291.appspot.com"
  },
  "client": [
    {
      "client_info": {
        "mobilesdk_app_id": "1:8400768666:android:2b6065e31659e7f6",
        "android_client_info": {
          "package_name": "com.imsghaziabad.imsghaziabad"
        }
      },
      "oauth_client": [
        {
          "client_id": "8400768666-cc2jkfg8balbqs34vu8dcts24e5liot5.apps.googleusercontent.com",
          "client_type": 3
        }
      ],
      "api_key": [
        {
          "current_key": "AIzaSyCKZap0KHU9Sxg0VMwB4_zaxpNLvGmb25c"
        }
      ],
      "services": {
        "analytics_service": {
          "status": 1
        },
        "appinvite_service": {
          "status": 1,
          "other_platform_oauth_client": []
        },
        "ads_service": {
          "status": 2
        }
      }
    }
  ],
  "configuration_version": "1"
}